{
    "_comment": "Tuya 4 Gangs Inching Relay command",
    "_version": "1.0",
    "Ep": {
        "01": {
            "0000": "",
            "0003": "",
            "0004": "",
            "0005": "",
            "0006": "",
            "e000": "",
            "e001": "",
            "000a": "",
            "0019": "",
            "Type": "Switch"
        },
        "02": {
            "0000": "",
            "0004": "",
            "0005": "",
            "0006": "",
            "e001": "",
            "Type": "Switch"
        },
        "03": {
            "0000": "",
            "0004": "",
            "0005": "",
            "0006": "",
            "e001": "",
            "Type": "Switch"
        },
        "04": {
            "0000": "",
            "0004": "",
            "0005": "",
            "0006": "",
            "e001": "",
            "Type": "Switch"
        },
        "f2": {
            "0021": "",
            "Type": ""
        }
    },
    "Type": "",
    "ClusterToBind": [
    ],
    "ConfigureReporting": {
    },
    "ReadAttributes": {
        "0000": [ "0004", "0000", "0001", "0005", "0007", "fffe", "0002", "0003", "0004", "0006" ],
        "0006": [ "0000", "4001", "4002", "5000", "8000", "8001", "8002" ],
        "e000": [ "d001", "d002", "d003" ],
        "e001": [ "d010" ],
        "0019": [ "0001", "0002", "0003", "0004", "0005", "0006", "0007", "0008", "0009" ]
    },
    "Param": {
        "SmartSwitchBackLight": 1,
        "SmartSwitchIndicateLight": 1,
        "PowerOnAfterOffOn": "0"
    }
}
